{"trial_id": "23", "hyperparameters": {"space": [{"class_name": "Int", "config": {"name": "num_layers", "default": 2, "conditions": [], "min_value": 1, "max_value": 10, "step": 1, "sampling": "linear"}}, {"class_name": "Choice", "config": {"name": "units", "default": 64, "conditions": [], "values": [16, 32, 64, 128, 256, 512], "ordered": true}}, {"class_name": "Choice", "config": {"name": "activation", "default": "relu", "conditions": [], "values": ["relu", "elu", "tanh"], "ordered": false}}, {"class_name": "Float", "config": {"name": "dropout_rate", "default": 0.0, "conditions": [], "min_value": 0.0, "max_value": 0.6, "step": null, "sampling": "linear"}}, {"class_name": "Boolean", "config": {"name": "use_batch_norm", "default": true, "conditions": []}}, {"class_name": "Boolean", "config": {"name": "use_residual", "default": false, "conditions": []}}, {"class_name": "Float", "config": {"name": "learning_rate", "default": 0.001, "conditions": [], "min_value": 1e-05, "max_value": 0.01, "step": null, "sampling": "log"}}], "values": {"num_layers": 10, "units": 16, "activation": "tanh", "dropout_rate": 0.2749526038975449, "use_batch_norm": true, "use_residual": false, "learning_rate": 0.00014543498328163732}}, "metrics": {"metrics": {"loss": {"direction": "min", "observations": [{"value": [27.60315704345703], "step": 9}]}, "mse": {"direction": "min", "observations": [{"value": [27.60315704345703], "step": 9}]}, "val_loss": {"direction": "min", "observations": [{"value": [412.0952453613281], "step": 9}]}, "val_mse": {"direction": "min", "observations": [{"value": [412.0952453613281], "step": 9}]}}}, "score": 412.0952453613281, "best_step": 9, "status": "COMPLETED", "message": null}