{"trial_id": "06", "hyperparameters": {"space": [{"class_name": "Choice", "config": {"name": "filters", "default": 32, "conditions": [], "values": [16, 32, 64, 128], "ordered": true}}, {"class_name": "Int", "config": {"name": "kernel_size", "default": 2, "conditions": [], "min_value": 1, "max_value": 3, "step": 1, "sampling": "linear"}}, {"class_name": "Choice", "config": {"name": "dense_units", "default": 64, "conditions": [], "values": [16, 32, 64, 128], "ordered": true}}, {"class_name": "Float", "config": {"name": "dropout_rate", "default": 0.5, "conditions": [], "min_value": 0.001, "max_value": 0.1, "step": null, "sampling": "linear"}}, {"class_name": "Float", "config": {"name": "learning_rate", "default": 0.001, "conditions": [], "min_value": 0.0001, "max_value": 0.01, "step": null, "sampling": "log"}}], "values": {"filters": 128, "kernel_size": 2, "dense_units": 128, "dropout_rate": 0.009943645572665603, "learning_rate": 0.008547485565344062}}, "metrics": {"metrics": {"loss": {"direction": "min", "observations": [{"value": [7.994922161102295], "step": 14}]}, "mse": {"direction": "min", "observations": [{"value": [7.994922161102295], "step": 14}]}, "val_loss": {"direction": "min", "observations": [{"value": [249.88937377929688], "step": 14}]}, "val_mse": {"direction": "min", "observations": [{"value": [249.88937377929688], "step": 14}]}}}, "score": 249.88937377929688, "best_step": 14, "status": "COMPLETED", "message": null}