{"trial_id": "14", "hyperparameters": {"space": [{"class_name": "Float", "config": {"name": "w_mon_inc", "default": 0.01, "conditions": [], "min_value": 0.0001, "max_value": 0.1, "step": null, "sampling": "log"}}, {"class_name": "Float", "config": {"name": "w_mon_dec", "default": 0.01, "conditions": [], "min_value": 0.0001, "max_value": 0.1, "step": null, "sampling": "log"}}, {"class_name": "Float", "config": {"name": "w_flat", "default": 0.01, "conditions": [], "min_value": 0.0001, "max_value": 0.1, "step": null, "sampling": "log"}}, {"class_name": "Float", "config": {"name": "w_shear_thinning", "default": 0.01, "conditions": [], "min_value": 0.0001, "max_value": 0.1, "step": null, "sampling": "log"}}, {"class_name": "Float", "config": {"name": "w_arhenius", "default": 0.01, "conditions": [], "min_value": 0.0001, "max_value": 0.1, "step": null, "sampling": "log"}}, {"class_name": "Float", "config": {"name": "w_pi_bell", "default": 0.01, "conditions": [], "min_value": 0.0001, "max_value": 0.1, "step": null, "sampling": "log"}}, {"class_name": "Float", "config": {"name": "w_einstein_threshold", "default": 0.01, "conditions": [], "min_value": 0.0001, "max_value": 0.1, "step": null, "sampling": "log"}}, {"class_name": "Float", "config": {"name": "w_einstein_dilute_limit", "default": 0.01, "conditions": [], "min_value": 0.0001, "max_value": 0.1, "step": null, "sampling": "log"}}, {"class_name": "Float", "config": {"name": "w_exclude_volume_divergence", "default": 0.01, "conditions": [], "min_value": 0.0001, "max_value": 0.1, "step": null, "sampling": "log"}}, {"class_name": "Int", "config": {"name": "num_layers", "default": null, "conditions": [], "min_value": 1, "max_value": 10, "step": 1, "sampling": "linear"}}, {"class_name": "Choice", "config": {"name": "activation", "default": "relu", "conditions": [], "values": ["relu", "tanh", "elu", "sine"], "ordered": false}}, {"class_name": "Float", "config": {"name": "l2_reg", "default": 1e-06, "conditions": [], "min_value": 1e-06, "max_value": 0.01, "step": null, "sampling": "log"}}, {"class_name": "Float", "config": {"name": "dropout_rate", "default": 0.0, "conditions": [], "min_value": 0.0, "max_value": 0.5, "step": 0.1, "sampling": "linear"}}, {"class_name": "Float", "config": {"name": "learning_rate", "default": 0.0001, "conditions": [], "min_value": 0.0001, "max_value": 0.01, "step": null, "sampling": "log"}}, {"class_name": "Int", "config": {"name": "units_0", "default": null, "conditions": [], "min_value": 16, "max_value": 256, "step": 16, "sampling": "linear"}}, {"class_name": "Choice", "config": {"name": "optimizer", "default": "adam", "conditions": [], "values": ["adam", "rmsprop", "sgd"], "ordered": false}}, {"class_name": "Int", "config": {"name": "units_1", "default": null, "conditions": [], "min_value": 16, "max_value": 256, "step": 16, "sampling": "linear"}}, {"class_name": "Int", "config": {"name": "units_2", "default": null, "conditions": [], "min_value": 16, "max_value": 256, "step": 16, "sampling": "linear"}}, {"class_name": "Int", "config": {"name": "units_3", "default": null, "conditions": [], "min_value": 16, "max_value": 256, "step": 16, "sampling": "linear"}}, {"class_name": "Int", "config": {"name": "units_4", "default": null, "conditions": [], "min_value": 16, "max_value": 256, "step": 16, "sampling": "linear"}}, {"class_name": "Int", "config": {"name": "units_5", "default": null, "conditions": [], "min_value": 16, "max_value": 256, "step": 16, "sampling": "linear"}}, {"class_name": "Int", "config": {"name": "units_6", "default": null, "conditions": [], "min_value": 16, "max_value": 256, "step": 16, "sampling": "linear"}}, {"class_name": "Int", "config": {"name": "units_7", "default": null, "conditions": [], "min_value": 16, "max_value": 256, "step": 16, "sampling": "linear"}}, {"class_name": "Int", "config": {"name": "units_8", "default": null, "conditions": [], "min_value": 16, "max_value": 256, "step": 16, "sampling": "linear"}}, {"class_name": "Int", "config": {"name": "units_9", "default": null, "conditions": [], "min_value": 16, "max_value": 256, "step": 16, "sampling": "linear"}}], "values": {"w_mon_inc": 0.0027483791557078685, "w_mon_dec": 0.0017884849799125367, "w_flat": 0.0337751691060949, "w_shear_thinning": 0.001586974819176836, "w_arhenius": 0.006774973315749124, "w_pi_bell": 0.00011822282410159204, "w_einstein_threshold": 0.00680009390208158, "w_einstein_dilute_limit": 0.06907128182383131, "w_exclude_volume_divergence": 0.0030495125744844148, "num_layers": 5, "activation": "elu", "l2_reg": 1.8081733732446794e-06, "dropout_rate": 0.30000000000000004, "learning_rate": 0.0009438228406975502, "units_0": 112, "optimizer": "rmsprop", "units_1": 48, "units_2": 32, "units_3": 48, "units_4": 144, "units_5": 160, "units_6": 160, "units_7": 112, "units_8": 208, "units_9": 80}}, "metrics": {"metrics": {"train_loss": {"direction": "min", "observations": [{"value": [61.06775665283203, 39.47160339355469, 29.307296752929688, 30.51506805419922, 29.980634689331055], "step": 0}]}, "mean_absolute_error": {"direction": "min", "observations": [{"value": [0.0, 0.0, 0.0, 0.0, 0.0], "step": 0}]}, "val_loss": {"direction": "min", "observations": [{"value": [19.588199615478516, 17.18246078491211, 13.960193634033203, 13.410555839538574, 15.314224243164062], "step": 0}]}}}, "score": 15.891126823425292, "best_step": 0, "status": "COMPLETED", "message": null}