{"trial_id": "13", "hyperparameters": {"space": [{"class_name": "Float", "config": {"name": "w_mon_inc", "default": 0.01, "conditions": [], "min_value": 0.0001, "max_value": 0.1, "step": null, "sampling": "log"}}, {"class_name": "Float", "config": {"name": "w_mon_dec", "default": 0.01, "conditions": [], "min_value": 0.0001, "max_value": 0.1, "step": null, "sampling": "log"}}, {"class_name": "Float", "config": {"name": "w_flat", "default": 0.01, "conditions": [], "min_value": 0.0001, "max_value": 0.1, "step": null, "sampling": "log"}}, {"class_name": "Float", "config": {"name": "w_shear_thinning", "default": 0.01, "conditions": [], "min_value": 0.0001, "max_value": 0.1, "step": null, "sampling": "log"}}, {"class_name": "Float", "config": {"name": "w_arhenius", "default": 0.01, "conditions": [], "min_value": 0.0001, "max_value": 0.1, "step": null, "sampling": "log"}}, {"class_name": "Float", "config": {"name": "w_pi_bell", "default": 0.01, "conditions": [], "min_value": 0.0001, "max_value": 0.1, "step": null, "sampling": "log"}}, {"class_name": "Float", "config": {"name": "w_einstein_threshold", "default": 0.01, "conditions": [], "min_value": 0.0001, "max_value": 0.1, "step": null, "sampling": "log"}}, {"class_name": "Float", "config": {"name": "w_einstein_dilute_limit", "default": 0.01, "conditions": [], "min_value": 0.0001, "max_value": 0.1, "step": null, "sampling": "log"}}, {"class_name": "Float", "config": {"name": "w_exclude_volume_divergence", "default": 0.01, "conditions": [], "min_value": 0.0001, "max_value": 0.1, "step": null, "sampling": "log"}}, {"class_name": "Int", "config": {"name": "num_layers", "default": null, "conditions": [], "min_value": 1, "max_value": 10, "step": 1, "sampling": "linear"}}, {"class_name": "Choice", "config": {"name": "activation", "default": "relu", "conditions": [], "values": ["relu", "tanh", "elu", "sine"], "ordered": false}}, {"class_name": "Float", "config": {"name": "l2_reg", "default": 1e-06, "conditions": [], "min_value": 1e-06, "max_value": 0.01, "step": null, "sampling": "log"}}, {"class_name": "Float", "config": {"name": "dropout_rate", "default": 0.0, "conditions": [], "min_value": 0.0, "max_value": 0.5, "step": 0.1, "sampling": "linear"}}, {"class_name": "Float", "config": {"name": "learning_rate", "default": 0.0001, "conditions": [], "min_value": 0.0001, "max_value": 0.01, "step": null, "sampling": "log"}}, {"class_name": "Int", "config": {"name": "units_0", "default": null, "conditions": [], "min_value": 16, "max_value": 256, "step": 16, "sampling": "linear"}}, {"class_name": "Choice", "config": {"name": "optimizer", "default": "adam", "conditions": [], "values": ["adam", "rmsprop", "sgd"], "ordered": false}}, {"class_name": "Int", "config": {"name": "units_1", "default": null, "conditions": [], "min_value": 16, "max_value": 256, "step": 16, "sampling": "linear"}}, {"class_name": "Int", "config": {"name": "units_2", "default": null, "conditions": [], "min_value": 16, "max_value": 256, "step": 16, "sampling": "linear"}}, {"class_name": "Int", "config": {"name": "units_3", "default": null, "conditions": [], "min_value": 16, "max_value": 256, "step": 16, "sampling": "linear"}}, {"class_name": "Int", "config": {"name": "units_4", "default": null, "conditions": [], "min_value": 16, "max_value": 256, "step": 16, "sampling": "linear"}}, {"class_name": "Int", "config": {"name": "units_5", "default": null, "conditions": [], "min_value": 16, "max_value": 256, "step": 16, "sampling": "linear"}}, {"class_name": "Int", "config": {"name": "units_6", "default": null, "conditions": [], "min_value": 16, "max_value": 256, "step": 16, "sampling": "linear"}}, {"class_name": "Int", "config": {"name": "units_7", "default": null, "conditions": [], "min_value": 16, "max_value": 256, "step": 16, "sampling": "linear"}}, {"class_name": "Int", "config": {"name": "units_8", "default": null, "conditions": [], "min_value": 16, "max_value": 256, "step": 16, "sampling": "linear"}}, {"class_name": "Int", "config": {"name": "units_9", "default": null, "conditions": [], "min_value": 16, "max_value": 256, "step": 16, "sampling": "linear"}}], "values": {"w_mon_inc": 0.00797469199943017, "w_mon_dec": 0.01646969379253835, "w_flat": 0.00026325922860621475, "w_shear_thinning": 0.00010608105501981827, "w_arhenius": 0.004299611617105448, "w_pi_bell": 0.07625347920850051, "w_einstein_threshold": 0.002250055565336202, "w_einstein_dilute_limit": 0.0006283915742570597, "w_exclude_volume_divergence": 0.00022081778104802579, "num_layers": 2, "activation": "relu", "l2_reg": 7.223406070786473e-06, "dropout_rate": 0.1, "learning_rate": 0.008948127145727224, "units_0": 224, "optimizer": "rmsprop", "units_1": 128, "units_2": 240, "units_3": 32, "units_4": 208, "units_5": 160, "units_6": 160, "units_7": 240, "units_8": 128, "units_9": 176}}, "metrics": {"metrics": {"train_loss": {"direction": "min", "observations": [{"value": [51.925296783447266, 32.13750457763672, 25.296146392822266, 22.205623626708984, 19.485904693603516], "step": 0}]}, "mean_absolute_error": {"direction": "min", "observations": [{"value": [0.0, 0.0, 0.0, 0.0, 0.0], "step": 0}]}, "val_loss": {"direction": "min", "observations": [{"value": [21.92681884765625, 12.430763244628906, 9.88023853302002, 7.29052734375, 7.249692440032959], "step": 0}]}}}, "score": 11.755608081817627, "best_step": 0, "status": "COMPLETED", "message": null}